polcalibration/__init__.py
polcalibration/function.py
polcalibration/polarizedsource.py
polcalibration/polcalibration.py
polcalibration/utils.py
polcalibration-0.0.1.dist-info/LICENSE
polcalibration-0.0.1.dist-info/METADATA
polcalibration-0.0.1.dist-info/WHEEL
polcalibration-0.0.1.dist-info/top_level.txt
polcalibration-0.0.1.dist-info/RECORD
