Metadata-Version: 2.1
Name: polcalibration
Version: 0.0.1
Summary: Object oriented scripts for polarization calibration
Home-page: https://github.com/miguelcarcamov/polcal_scripts
Author: Miguel Carcamo
Author-email: miguel.carcamo@manchester.ac.uk
License: GNU
Platform: UNKNOWN
Classifier: Programming Language :: Python :: 3
Classifier: License :: OSI Approved :: GNU General Public License v3 (GPLv3)
Classifier: Operating System :: OS Independent
